MANIFEST.in
README.rst
setup.py
nbhood_core/__init__.py
nbhood_core/admin.py
nbhood_core/apps.py
nbhood_core/models.py
nbhood_core/serializers.py
nbhood_core/tests.py
nbhood_core/views.py
nbhood_core/migrations/0001_initial.py
nbhood_core/migrations/0002_contact.py
nbhood_core/migrations/__init__.py
nbhood_static_pages.egg-info/PKG-INFO
nbhood_static_pages.egg-info/SOURCES.txt
nbhood_static_pages.egg-info/dependency_links.txt
nbhood_static_pages.egg-info/not-zip-safe
nbhood_static_pages.egg-info/top_level.txt