Metadata-Version: 1.1
Name: nbhood-static-pages
Version: 0.1.8
Summary: A simple Django app to conduct Web-based polls.
Home-page: https://github.com/georgesamy/nbhood-static
Author: George Samy
Author-email: georgesamy0@gmail.com
License: BSD License
Platform: UNKNOWN
Classifier: Environment :: Web Environment
Classifier: Framework :: Django
Classifier: Intended Audience :: Developers
Classifier: License :: OSI Approved :: BSD License
Classifier: Operating System :: OS Independent
Classifier: Programming Language :: Python
Classifier: Programming Language :: Python :: 2.7
Classifier: Topic :: Internet :: WWW/HTTP
Classifier: Topic :: Internet :: WWW/HTTP :: Dynamic Content
